README.rst
setup.py
django_OneTimePassword/__init__.py
django_OneTimePassword/backends.py
django_OneTimePassword/conf.py
django_OneTimePassword/generators.py
django_OneTimePassword/models.py
django_OneTimePassword/tests.py
django_OneTimePassword.egg-info/PKG-INFO
django_OneTimePassword.egg-info/SOURCES.txt
django_OneTimePassword.egg-info/dependency_links.txt
django_OneTimePassword.egg-info/top_level.txt